LICENSE
MANIFEST.in
setup.py
readingtime/__init__.py
readingtime/wagtail_hooks.py
readingtime/static/api-monkeypatch.js
readingtime/static/readingtime.bundle.js
wagtail_readingtime.egg-info/PKG-INFO
wagtail_readingtime.egg-info/SOURCES.txt
wagtail_readingtime.egg-info/dependency_links.txt
wagtail_readingtime.egg-info/not-zip-safe
wagtail_readingtime.egg-info/requires.txt
wagtail_readingtime.egg-info/top_level.txt