Metadata-Version: 1.0
Name: wagtail-readingtime
Version: 1.1.1
Summary: Determine approximate reading time of a piece of text.
Home-page: https://github.com/vixdigital/wagtail-reading-time
Author: VIX Digital
Author-email: info@vix.digital
License: MIT
Platform: UNKNOWN
